dndfog/__init__.py
dndfog/_aoe.py
dndfog/camera.py
dndfog/draw/__init__.py
dndfog/draw/generic.py
dndfog/draw/map.py
dndfog/draw/toolbar.py
dndfog/event_handlers.py
dndfog/fog.py
dndfog/gameloop.py
dndfog/grid.py
dndfog/main.py
dndfog/map.py
dndfog/markings.py
dndfog/math.py
dndfog/piece.py
dndfog/saving.py
dndfog/toolbar.py
dndfog/types.py
LICENSE
README.md
dndfog-0.6.5.dist-info/entry_points.txt
dndfog-0.6.5.dist-info/LICENSE
dndfog-0.6.5.dist-info/METADATA
dndfog-0.6.5.dist-info/WHEEL
dndfog-0.6.5.dist-info/RECORD
