Metadata-Version: 2.1
Name: dndfog
Version: 0.6.5
Summary: DND battle map with fog of war
Home-page: https://mrthearman.github.io/dndfog/
License: MIT
Keywords: dnd,fog,war,map,combat,infinite,gird
Author: Matti Lamppu
Author-email: lamppu.matti.akseli@gmail.com
Requires-Python: >=3.10,<3.13
Classifier: Intended Audience :: End Users/Desktop
Classifier: License :: OSI Approved :: MIT License
Classifier: Natural Language :: English
Classifier: Operating System :: Microsoft :: Windows
Classifier: Operating System :: Microsoft :: Windows :: Windows 11
Classifier: Programming Language :: Python
Classifier: Programming Language :: Python :: 3
Classifier: Programming Language :: Python :: 3.10
Classifier: Programming Language :: Python :: 3.11
Classifier: Programming Language :: Python :: 3 :: Only
Classifier: Programming Language :: Python :: 3.12
Requires-Dist: pygame-ce (>=2.4.0)
Requires-Dist: pywin32 (>=306)
Project-URL: Repository, https://github.com/MrThearMan/dndfog
